[
  {
    "time": "Live",
    "artist": "Sepultura",
    "title": "Roots Bloody Roots",
    "timestamp": "2025-10-29T08:23:44.053358+01:00"
  },
  {
    "time": "01:17",
    "artist": "Kaiser Chiefs",
    "title": "Never Miss a Beat",
    "timestamp": "2025-10-29T01:17:00+01:00"
  },
  {
    "time": "01:12",
    "artist": "Live",
    "title": "Run To The Water",
    "timestamp": "2025-10-29T01:12:00+01:00"
  },
  {
    "time": "01:09",
    "artist": "The Smiths",
    "title": "Girlfriend in a Coma",
    "timestamp": "2025-10-29T01:09:00+01:00"
  },
  {
    "time": "01:06",
    "artist": "Muse",
    "title": "Mercy",
    "timestamp": "2025-10-29T01:06:00+01:00"
  },
  {
    "time": "00:56",
    "artist": "Crash Test Dummies",
    "title": "Mmm Mmm Mmm Mmm",
    "timestamp": "2025-10-29T00:56:00+01:00"
  },
  {
    "time": "00:52",
    "artist": "Foo Fighters",
    "title": "Let It Die",
    "timestamp": "2025-10-29T00:52:00+01:00"
  },
  {
    "time": "00:48",
    "artist": "Simple Minds",
    "title": "Promised You A Miracle",
    "timestamp": "2025-10-29T00:48:00+01:00"
  },
  {
    "time": "00:43",
    "artist": "Rammstein",
    "title": "Radio",
    "timestamp": "2025-10-29T00:43:00+01:00"
  },
  {
    "time": "00:38",
    "artist": "Keane",
    "title": "Everybody's Changing",
    "timestamp": "2025-10-29T00:38:00+01:00"
  },
  {
    "time": "00:35",
    "artist": "Tracy Bonham",
    "title": "Mother Mother",
    "timestamp": "2025-10-29T00:35:00+01:00"
  },
  {
    "time": "00:27",
    "artist": "Jesus and Mary Chain",
    "title": "Just Like Honey",
    "timestamp": "2025-10-29T00:27:00+01:00"
  },
  {
    "time": "00:21",
    "artist": "Aerosmith",
    "title": "Livin' On The Edge",
    "timestamp": "2025-10-29T00:21:00+01:00"
  },
  {
    "time": "00:18",
    "artist": "Sam Fender",
    "title": "Will We Talk?",
    "timestamp": "2025-10-29T00:18:00+01:00"
  },
  {
    "time": "00:15",
    "artist": "Evanescence",
    "title": "Going Under",
    "timestamp": "2025-10-29T00:15:00+01:00"
  },
  {
    "time": "00:10",
    "artist": "Depeche Mode",
    "title": "Strangelove",
    "timestamp": "2025-10-29T00:10:00+01:00"
  },
  {
    "time": "00:06",
    "artist": "Bush",
    "title": "Comedown",
    "timestamp": "2025-10-29T00:06:00+01:00"
  }
]