[
  {
    "time": "Live",
    "artist": "Placebo",
    "title": "Pure Morning",
    "timestamp": "2026-03-04T20:39:17.015168+01:00"
  },
  {
    "time": "11:32",
    "artist": "Nothing But Thieves",
    "title": "Particles (Piano Version)",
    "timestamp": "2026-03-04T11:32:00+01:00"
  },
  {
    "time": "11:25",
    "artist": "Aerosmith",
    "title": "Janie's Got A Gun",
    "timestamp": "2026-03-04T11:25:00+01:00"
  },
  {
    "time": "11:20",
    "artist": "Villanelle",
    "title": "Placebo",
    "timestamp": "2026-03-04T11:20:00+01:00"
  },
  {
    "time": "11:15",
    "artist": "Alanis Morissette",
    "title": "Head Over Feet",
    "timestamp": "2026-03-04T11:15:00+01:00"
  },
  {
    "time": "11:09",
    "artist": "White Lies",
    "title": "Juice",
    "timestamp": "2026-03-04T11:09:00+01:00"
  },
  {
    "time": "11:05",
    "artist": "Editors",
    "title": "Bones",
    "timestamp": "2026-03-04T11:05:00+01:00"
  },
  {
    "time": "10:59",
    "artist": "Violet Grohl",
    "title": "THUM",
    "timestamp": "2026-03-04T10:59:00+01:00"
  },
  {
    "time": "10:53",
    "artist": "Massive Attack",
    "title": "Teardrop",
    "timestamp": "2026-03-04T10:53:00+01:00"
  },
  {
    "time": "10:49",
    "artist": "Hard-Fi",
    "title": "They Ain't Your Friends",
    "timestamp": "2026-03-04T10:49:00+01:00"
  },
  {
    "time": "10:45",
    "artist": "Blaudzun",
    "title": "Elephants",
    "timestamp": "2026-03-04T10:45:00+01:00"
  },
  {
    "time": "10:40",
    "artist": "Deftones",
    "title": "Infinite Source",
    "timestamp": "2026-03-04T10:40:00+01:00"
  },
  {
    "time": "10:35",
    "artist": "Simple Minds",
    "title": "New Gold Dream (81–82–83–84)",
    "timestamp": "2026-03-04T10:35:00+01:00"
  },
  {
    "time": "10:27",
    "artist": "Kings Of Leon",
    "title": "Fans",
    "timestamp": "2026-03-04T10:27:00+01:00"
  },
  {
    "time": "10:22",
    "artist": "Bush",
    "title": "Machinehead",
    "timestamp": "2026-03-04T10:22:00+01:00"
  },
  {
    "time": "10:20",
    "artist": "Fit",
    "title": "Rewrite History",
    "timestamp": "2026-03-04T10:20:00+01:00"
  },
  {
    "time": "10:16",
    "artist": "Prince",
    "title": "When Doves Cry",
    "timestamp": "2026-03-04T10:16:00+01:00"
  },
  {
    "time": "10:13",
    "artist": "Jet",
    "title": "Are You Gonna Be My Girl",
    "timestamp": "2026-03-04T10:13:00+01:00"
  },
  {
    "time": "10:08",
    "artist": "The Black Keys",
    "title": "You Got To Lose",
    "timestamp": "2026-03-04T10:08:00+01:00"
  },
  {
    "time": "10:05",
    "artist": "Pearl Jam",
    "title": "Elderly Woman Behind The Counter In A Small Town",
    "timestamp": "2026-03-04T10:05:00+01:00"
  },
  {
    "time": "09:57",
    "artist": "Novastar",
    "title": "Because",
    "timestamp": "2026-03-04T09:57:00+01:00"
  },
  {
    "time": "09:53",
    "artist": "The Boxer Rebellion",
    "title": "Flowers In The Water",
    "timestamp": "2026-03-04T09:53:00+01:00"
  },
  {
    "time": "09:47",
    "artist": "Metallica",
    "title": "Sad But True",
    "timestamp": "2026-03-04T09:47:00+01:00"
  },
  {
    "time": "09:42",
    "artist": "Arcade Fire",
    "title": "Everything Now",
    "timestamp": "2026-03-04T09:42:00+01:00"
  },
  {
    "time": "09:38",
    "artist": "Franz Ferdinand",
    "title": "Take Me Out",
    "timestamp": "2026-03-04T09:38:00+01:00"
  },
  {
    "time": "09:34",
    "artist": "Biffy Clyro",
    "title": "Goodbye",
    "timestamp": "2026-03-04T09:34:00+01:00"
  },
  {
    "time": "09:30",
    "artist": "Red Hot Chili Peppers",
    "title": "Around the World",
    "timestamp": "2026-03-04T09:30:00+01:00"
  },
  {
    "time": "09:24",
    "artist": "Fun Lovin' Criminals",
    "title": "Scooby Snacks",
    "timestamp": "2026-03-04T09:24:00+01:00"
  },
  {
    "time": "09:21",
    "artist": "Cage the Elephant",
    "title": "Ain't No Rest for the Wicked",
    "timestamp": "2026-03-04T09:21:00+01:00"
  },
  {
    "time": "09:17",
    "artist": "Volbeat",
    "title": "Lola Montez",
    "timestamp": "2026-03-04T09:17:00+01:00"
  },
  {
    "time": "09:13",
    "artist": "Marcy Playground",
    "title": "Sex and Candy",
    "timestamp": "2026-03-04T09:13:00+01:00"
  },
  {
    "time": "09:10",
    "artist": "Wodan Boys & Barry Hay",
    "title": "Don't Be Silly",
    "timestamp": "2026-03-04T09:10:00+01:00"
  },
  {
    "time": "09:05",
    "artist": "New Order",
    "title": "True Faith",
    "timestamp": "2026-03-04T09:05:00+01:00"
  },
  {
    "time": "09:01",
    "artist": "Evanescence",
    "title": "Going Under",
    "timestamp": "2026-03-04T09:01:00+01:00"
  },
  {
    "time": "08:51",
    "artist": "Stone Temple Pilots",
    "title": "Plush",
    "timestamp": "2026-03-04T08:51:00+01:00"
  },
  {
    "time": "08:48",
    "artist": "The Kooks",
    "title": "Always Where I Need To Be",
    "timestamp": "2026-03-04T08:48:00+01:00"
  },
  {
    "time": "08:45",
    "artist": "Pogues",
    "title": "Dirty Old Town",
    "timestamp": "2026-03-04T08:45:00+01:00"
  },
  {
    "time": "08:41",
    "artist": "Ist Ist",
    "title": "Obligations",
    "timestamp": "2026-03-04T08:41:00+01:00"
  },
  {
    "time": "08:36",
    "artist": "Bloodhound Gang",
    "title": "Fire Water Burn",
    "timestamp": "2026-03-04T08:36:00+01:00"
  },
  {
    "time": "08:29",
    "artist": "Kaiser Chiefs",
    "title": "Never Miss a Beat",
    "timestamp": "2026-03-04T08:29:00+01:00"
  },
  {
    "time": "08:24",
    "artist": "The National",
    "title": "Bloodbuzz Ohio",
    "timestamp": "2026-03-04T08:24:00+01:00"
  },
  {
    "time": "08:20",
    "artist": "New Radicals",
    "title": "You Get What You Give",
    "timestamp": "2026-03-04T08:20:00+01:00"
  },
  {
    "time": "08:15",
    "artist": "Stone Sour",
    "title": "Through Glass",
    "timestamp": "2026-03-04T08:15:00+01:00"
  },
  {
    "time": "08:12",
    "artist": "Bleech 9:3",
    "title": "Jacky",
    "timestamp": "2026-03-04T08:12:00+01:00"
  },
  {
    "time": "08:08",
    "artist": "The Cure",
    "title": "Lullaby",
    "timestamp": "2026-03-04T08:08:00+01:00"
  },
  {
    "time": "08:04",
    "artist": "Placebo & David Bowie",
    "title": "Without You I'm Nothing",
    "timestamp": "2026-03-04T08:04:00+01:00"
  },
  {
    "time": "07:54",
    "artist": "Bloc Party",
    "title": "Helicopter",
    "timestamp": "2026-03-04T07:54:00+01:00"
  },
  {
    "time": "07:51",
    "artist": "Gorillaz",
    "title": "Orange County",
    "timestamp": "2026-03-04T07:51:00+01:00"
  },
  {
    "time": "07:47",
    "artist": "Chumbawamba",
    "title": "Tubthumping",
    "timestamp": "2026-03-04T07:47:00+01:00"
  },
  {
    "time": "07:44",
    "artist": "Pixies",
    "title": "Debaser",
    "timestamp": "2026-03-04T07:44:00+01:00"
  },
  {
    "time": "07:41",
    "artist": "Nothing But Thieves",
    "title": "Sorry",
    "timestamp": "2026-03-04T07:41:00+01:00"
  },
  {
    "time": "07:37",
    "artist": "Two Door Cinema Club",
    "title": "Something Good Can Work",
    "timestamp": "2026-03-04T07:37:00+01:00"
  },
  {
    "time": "07:33",
    "artist": "Foo Fighters",
    "title": "Monkey Wrench",
    "timestamp": "2026-03-04T07:33:00+01:00"
  },
  {
    "time": "07:24",
    "artist": "SONS",
    "title": "Somehow",
    "timestamp": "2026-03-04T07:24:00+01:00"
  },
  {
    "time": "07:21",
    "artist": "3 Doors Down",
    "title": "Kryptonite",
    "timestamp": "2026-03-04T07:21:00+01:00"
  },
  {
    "time": "07:17",
    "artist": "Depeche Mode",
    "title": "People are People",
    "timestamp": "2026-03-04T07:17:00+01:00"
  },
  {
    "time": "07:14",
    "artist": "Triggerfinger",
    "title": "Come Clean",
    "timestamp": "2026-03-04T07:14:00+01:00"
  },
  {
    "time": "07:10",
    "artist": "Thelonious Monster",
    "title": "Body And Soul",
    "timestamp": "2026-03-04T07:10:00+01:00"
  },
  {
    "time": "07:05",
    "artist": "Elephant",
    "title": "Reptile Zoo",
    "timestamp": "2026-03-04T07:05:00+01:00"
  },
  {
    "time": "07:02",
    "artist": "Linkin' Park",
    "title": "What I've Done",
    "timestamp": "2026-03-04T07:02:00+01:00"
  },
  {
    "time": "06:52",
    "artist": "Pearl Jam",
    "title": "Given To Fly",
    "timestamp": "2026-03-04T06:52:00+01:00"
  },
  {
    "time": "06:50",
    "artist": "Honey I'm Home",
    "title": "Pretty",
    "timestamp": "2026-03-04T06:50:00+01:00"
  },
  {
    "time": "06:46",
    "artist": "Snow Patrol",
    "title": "Run",
    "timestamp": "2026-03-04T06:46:00+01:00"
  },
  {
    "time": "06:44",
    "artist": "Ramones",
    "title": "Rock 'n' Roll High School",
    "timestamp": "2026-03-04T06:44:00+01:00"
  },
  {
    "time": "06:40",
    "artist": "Sam Fender",
    "title": "Rein Me In (ft. Olivia Dean)",
    "timestamp": "2026-03-04T06:40:00+01:00"
  },
  {
    "time": "06:36",
    "artist": "Live",
    "title": "I Alone",
    "timestamp": "2026-03-04T06:36:00+01:00"
  },
  {
    "time": "06:32",
    "artist": "Florence The Machine",
    "title": "Shake It Out",
    "timestamp": "2026-03-04T06:32:00+01:00"
  },
  {
    "time": "06:24",
    "artist": "Fall Out Boy",
    "title": "Sugar, We're Going Down",
    "timestamp": "2026-03-04T06:24:00+01:00"
  },
  {
    "time": "06:20",
    "artist": "Radiohead",
    "title": "High & Dry",
    "timestamp": "2026-03-04T06:20:00+01:00"
  },
  {
    "time": "06:16",
    "artist": "M83",
    "title": "Reunion",
    "timestamp": "2026-03-04T06:16:00+01:00"
  },
  {
    "time": "06:13",
    "artist": "Sex Pistols",
    "title": "Anarchy in the UK",
    "timestamp": "2026-03-04T06:13:00+01:00"
  },
  {
    "time": "06:08",
    "artist": "Coldplay",
    "title": "Fix You",
    "timestamp": "2026-03-04T06:08:00+01:00"
  },
  {
    "time": "06:05",
    "artist": "ALEXSUCKS",
    "title": "Autopilot",
    "timestamp": "2026-03-04T06:05:00+01:00"
  },
  {
    "time": "06:02",
    "artist": "Nirvana",
    "title": "Rape Me",
    "timestamp": "2026-03-04T06:02:00+01:00"
  },
  {
    "time": "05:54",
    "artist": "Arctic Monkeys",
    "title": "Opening Night",
    "timestamp": "2026-03-04T05:54:00+01:00"
  },
  {
    "time": "05:50",
    "artist": "R.E.M.",
    "title": "What's The Frequency Kenneth",
    "timestamp": "2026-03-04T05:50:00+01:00"
  },
  {
    "time": "05:47",
    "artist": "Twenty One Pilots",
    "title": "Ride",
    "timestamp": "2026-03-04T05:47:00+01:00"
  },
  {
    "time": "05:42",
    "artist": "Wolfmother",
    "title": "Joker & The Thief",
    "timestamp": "2026-03-04T05:42:00+01:00"
  },
  {
    "time": "05:38",
    "artist": "Mumford & Sons, Hozier",
    "title": "Rubber Band Man",
    "timestamp": "2026-03-04T05:38:00+01:00"
  },
  {
    "time": "05:33",
    "artist": "Faith No More",
    "title": "Epic",
    "timestamp": "2026-03-04T05:33:00+01:00"
  },
  {
    "time": "05:27",
    "artist": "Carolina Liar",
    "title": "Show Me What I'm Looking For",
    "timestamp": "2026-03-04T05:27:00+01:00"
  },
  {
    "time": "05:18",
    "artist": "Yungblud",
    "title": "Hello Heaven Hello",
    "timestamp": "2026-03-04T05:18:00+01:00"
  },
  {
    "time": "05:13",
    "artist": "The Cranberries",
    "title": "Linger",
    "timestamp": "2026-03-04T05:13:00+01:00"
  },
  {
    "time": "05:10",
    "artist": "Hiqpy",
    "title": "Youman",
    "timestamp": "2026-03-04T05:10:00+01:00"
  },
  {
    "time": "05:06",
    "artist": "Stealers Wheel",
    "title": "Stuck In The Middle With You",
    "timestamp": "2026-03-04T05:06:00+01:00"
  },
  {
    "time": "05:02",
    "artist": "Queens Of The Stone Age",
    "title": "Make It Wit Chu",
    "timestamp": "2026-03-04T05:02:00+01:00"
  },
  {
    "time": "04:55",
    "artist": "The Haunted Youth",
    "title": "deathwish (ft. Max Fry)",
    "timestamp": "2026-03-04T04:55:00+01:00"
  },
  {
    "time": "04:51",
    "artist": "The Cardigans",
    "title": "Lovefool",
    "timestamp": "2026-03-04T04:51:00+01:00"
  },
  {
    "time": "04:47",
    "artist": "Bruce Springsteen",
    "title": "Born to Run",
    "timestamp": "2026-03-04T04:47:00+01:00"
  },
  {
    "time": "04:44",
    "artist": "The Vices",
    "title": "I Know",
    "timestamp": "2026-03-04T04:44:00+01:00"
  },
  {
    "time": "04:40",
    "artist": "Hooverphonic",
    "title": "Mad About You",
    "timestamp": "2026-03-04T04:40:00+01:00"
  },
  {
    "time": "04:35",
    "artist": "Band of Horses",
    "title": "The Funeral",
    "timestamp": "2026-03-04T04:35:00+01:00"
  },
  {
    "time": "04:32",
    "artist": "Zebrahead",
    "title": "Playmate of the Year",
    "timestamp": "2026-03-04T04:32:00+01:00"
  },
  {
    "time": "04:22",
    "artist": "Soundgarden",
    "title": "Black Hole Sun",
    "timestamp": "2026-03-04T04:22:00+01:00"
  },
  {
    "time": "04:18",
    "artist": "Incubus",
    "title": "Drive",
    "timestamp": "2026-03-04T04:18:00+01:00"
  },
  {
    "time": "04:14",
    "artist": "Stone",
    "title": "Stack Up The Reasons",
    "timestamp": "2026-03-04T04:14:00+01:00"
  },
  {
    "time": "04:10",
    "artist": "Melissa Etheridge",
    "title": "Bring Me Some Water",
    "timestamp": "2026-03-04T04:10:00+01:00"
  },
  {
    "time": "04:06",
    "artist": "Muse",
    "title": "Resistance",
    "timestamp": "2026-03-04T04:06:00+01:00"
  },
  {
    "time": "04:01",
    "artist": "Arcade Fire",
    "title": "We Used to Wait",
    "timestamp": "2026-03-04T04:01:00+01:00"
  },
  {
    "time": "03:53",
    "artist": "The White Stripes",
    "title": "Seven Nation Army",
    "timestamp": "2026-03-04T03:53:00+01:00"
  },
  {
    "time": "03:49",
    "artist": "U2",
    "title": "American Obituary",
    "timestamp": "2026-03-04T03:49:00+01:00"
  },
  {
    "time": "03:45",
    "artist": "Suede",
    "title": "Trash",
    "timestamp": "2026-03-04T03:45:00+01:00"
  },
  {
    "time": "03:41",
    "artist": "Lou Reed",
    "title": "Walk On The Wild Side",
    "timestamp": "2026-03-04T03:41:00+01:00"
  },
  {
    "time": "03:36",
    "artist": "Blink-182",
    "title": "Adam's Song",
    "timestamp": "2026-03-04T03:36:00+01:00"
  },
  {
    "time": "03:32",
    "artist": "Editors",
    "title": "Sugar",
    "timestamp": "2026-03-04T03:32:00+01:00"
  },
  {
    "time": "03:26",
    "artist": "Guns N' Roses",
    "title": "You Could Be Mine",
    "timestamp": "2026-03-04T03:26:00+01:00"
  },
  {
    "time": "03:19",
    "artist": "Kings of Leon",
    "title": "To Space",
    "timestamp": "2026-03-04T03:19:00+01:00"
  },
  {
    "time": "03:16",
    "artist": "dEUS",
    "title": "The Architect",
    "timestamp": "2026-03-04T03:16:00+01:00"
  },
  {
    "time": "03:13",
    "artist": "Led Zeppelin",
    "title": "Immigrant Song",
    "timestamp": "2026-03-04T03:13:00+01:00"
  },
  {
    "time": "03:10",
    "artist": "The Black Keys",
    "title": "You Got To Lose",
    "timestamp": "2026-03-04T03:10:00+01:00"
  },
  {
    "time": "03:06",
    "artist": "Foo Fighters",
    "title": "This Is A Call",
    "timestamp": "2026-03-04T03:06:00+01:00"
  },
  {
    "time": "03:03",
    "artist": "Turnstile",
    "title": "Seein' Stars",
    "timestamp": "2026-03-04T03:03:00+01:00"
  },
  {
    "time": "02:58",
    "artist": "White Lies",
    "title": "Farewell To The Fairground",
    "timestamp": "2026-03-04T02:58:00+01:00"
  },
  {
    "time": "02:52",
    "artist": "Wodan Boys & Barry Hay",
    "title": "Don't Be Silly",
    "timestamp": "2026-03-04T02:52:00+01:00"
  },
  {
    "time": "02:49",
    "artist": "The Verve",
    "title": "Sonnet",
    "timestamp": "2026-03-04T02:49:00+01:00"
  },
  {
    "time": "02:44",
    "artist": "The Verve",
    "title": "Lucky Man",
    "timestamp": "2026-03-04T02:44:00+01:00"
  },
  {
    "time": "02:39",
    "artist": "Bad Omens",
    "title": "Dying To Love",
    "timestamp": "2026-03-04T02:39:00+01:00"
  },
  {
    "time": "02:34",
    "artist": "Kate Bush",
    "title": "Cloudbusting",
    "timestamp": "2026-03-04T02:34:00+01:00"
  },
  {
    "time": "02:30",
    "artist": "Florence The Machine",
    "title": "Ship to Wreck",
    "timestamp": "2026-03-04T02:30:00+01:00"
  },
  {
    "time": "02:24",
    "artist": "Kaiser Chiefs",
    "title": "Everything Is Average Nowadays",
    "timestamp": "2026-03-04T02:24:00+01:00"
  },
  {
    "time": "02:21",
    "artist": "The Offspring",
    "title": "Come Out And Play",
    "timestamp": "2026-03-04T02:21:00+01:00"
  },
  {
    "time": "02:17",
    "artist": "Vampire Weekend",
    "title": "Harmony Hall",
    "timestamp": "2026-03-04T02:17:00+01:00"
  },
  {
    "time": "02:14",
    "artist": "Zz Top",
    "title": "La Grange",
    "timestamp": "2026-03-04T02:14:00+01:00"
  },
  {
    "time": "02:10",
    "artist": "Weezer",
    "title": "Island in the Sun",
    "timestamp": "2026-03-04T02:10:00+01:00"
  },
  {
    "time": "02:06",
    "artist": "Yungblud",
    "title": "Suburban Requiem",
    "timestamp": "2026-03-04T02:06:00+01:00"
  },
  {
    "time": "02:01",
    "artist": "The Smashing Pumpkins",
    "title": "Bullet With Butterfly Wings",
    "timestamp": "2026-03-04T02:01:00+01:00"
  },
  {
    "time": "01:52",
    "artist": "Neil Young",
    "title": "Rockin' In The Free World",
    "timestamp": "2026-03-04T01:52:00+01:00"
  },
  {
    "time": "01:50",
    "artist": "Honey I'm Home",
    "title": "Pretty",
    "timestamp": "2026-03-04T01:50:00+01:00"
  },
  {
    "time": "01:47",
    "artist": "Nothing But Thieves",
    "title": "Welcome To The DCC",
    "timestamp": "2026-03-04T01:47:00+01:00"
  },
  {
    "time": "01:44",
    "artist": "Bad Religion",
    "title": "21 Century (Digital Boy)",
    "timestamp": "2026-03-04T01:44:00+01:00"
  },
  {
    "time": "01:38",
    "artist": "Snow Patrol",
    "title": "Chasing Cars",
    "timestamp": "2026-03-04T01:38:00+01:00"
  },
  {
    "time": "01:34",
    "artist": "Sam Fender",
    "title": "Talk To You (feat. Elton John)",
    "timestamp": "2026-03-04T01:34:00+01:00"
  },
  {
    "time": "01:31",
    "artist": "Alice in Chains",
    "title": "Would",
    "timestamp": "2026-03-04T01:31:00+01:00"
  },
  {
    "time": "01:22",
    "artist": "Garbage",
    "title": "Stupid Girl",
    "timestamp": "2026-03-04T01:22:00+01:00"
  },
  {
    "time": "01:19",
    "artist": "R.E.M.",
    "title": "Imitation of Life",
    "timestamp": "2026-03-04T01:19:00+01:00"
  },
  {
    "time": "01:14",
    "artist": "Volbeat",
    "title": "Heaven Nor Hell",
    "timestamp": "2026-03-04T01:14:00+01:00"
  },
  {
    "time": "01:10",
    "artist": "The Verve Pipe",
    "title": "Freshmen",
    "timestamp": "2026-03-04T01:10:00+01:00"
  },
  {
    "time": "01:07",
    "artist": "Ist Ist",
    "title": "Obligations",
    "timestamp": "2026-03-04T01:07:00+01:00"
  },
  {
    "time": "01:05",
    "artist": "The Kinks",
    "title": "You Really Got Me",
    "timestamp": "2026-03-04T01:05:00+01:00"
  },
  {
    "time": "01:01",
    "artist": "30 Seconds To Mars",
    "title": "The Kill (Bury Me)",
    "timestamp": "2026-03-04T01:01:00+01:00"
  },
  {
    "time": "00:53",
    "artist": "De Staat",
    "title": "Make The Call, Leave It All",
    "timestamp": "2026-03-04T00:53:00+01:00"
  },
  {
    "time": "00:50",
    "artist": "Pearl Jam",
    "title": "Just Breathe",
    "timestamp": "2026-03-04T00:50:00+01:00"
  },
  {
    "time": "00:47",
    "artist": "Triggerfinger",
    "title": "Come Clean",
    "timestamp": "2026-03-04T00:47:00+01:00"
  },
  {
    "time": "00:43",
    "artist": "The Cure",
    "title": "Lovesong",
    "timestamp": "2026-03-04T00:43:00+01:00"
  },
  {
    "time": "00:39",
    "artist": "Red Hot Chili Peppers",
    "title": "Tell Me Baby",
    "timestamp": "2026-03-04T00:39:00+01:00"
  },
  {
    "time": "00:35",
    "artist": "Twenty One Pilots",
    "title": "Drum Show",
    "timestamp": "2026-03-04T00:35:00+01:00"
  },
  {
    "time": "00:32",
    "artist": "Blur",
    "title": "Parklife",
    "timestamp": "2026-03-04T00:32:00+01:00"
  },
  {
    "time": "00:25",
    "artist": "The Doors",
    "title": "Light My Fire",
    "timestamp": "2026-03-04T00:25:00+01:00"
  },
  {
    "time": "00:22",
    "artist": "Biffy Clyro",
    "title": "Many of Horror",
    "timestamp": "2026-03-04T00:22:00+01:00"
  },
  {
    "time": "00:19",
    "artist": "Arctic Monkeys",
    "title": "Brianstorm",
    "timestamp": "2026-03-04T00:19:00+01:00"
  },
  {
    "time": "00:17",
    "artist": "Violet Grohl",
    "title": "THUM",
    "timestamp": "2026-03-04T00:17:00+01:00"
  },
  {
    "time": "00:13",
    "artist": "Smash Mouth",
    "title": "All Star",
    "timestamp": "2026-03-04T00:13:00+01:00"
  },
  {
    "time": "00:09",
    "artist": "Faith No More",
    "title": "Evidence",
    "timestamp": "2026-03-04T00:09:00+01:00"
  },
  {
    "time": "00:05",
    "artist": "Bush",
    "title": "Swallowed",
    "timestamp": "2026-03-04T00:05:00+01:00"
  }
]