[
  {
    "time": "01:50",
    "artist": "Evanescence",
    "title": "Afterlife",
    "timestamp": "2025-06-16T01:50:00+02:00"
  },
  {
    "time": "01:46",
    "artist": "The Rolling Stones",
    "title": "Satisfaction",
    "timestamp": "2025-06-16T01:46:00+02:00"
  },
  {
    "time": "01:40",
    "artist": "Carolina Liar",
    "title": "Show Me What I'm Looking For",
    "timestamp": "2025-06-16T01:40:00+02:00"
  },
  {
    "time": "01:36",
    "artist": "The Vices",
    "title": "Shaking Shoulder",
    "timestamp": "2025-06-16T01:36:00+02:00"
  },
  {
    "time": "01:32",
    "artist": "Red Hot Chili Peppers",
    "title": "Under The Bridge",
    "timestamp": "2025-06-16T01:32:00+02:00"
  },
  {
    "time": "01:24",
    "artist": "Jett Rebel",
    "title": "Do You Love Me At All",
    "timestamp": "2025-06-16T01:24:00+02:00"
  },
  {
    "time": "01:19",
    "artist": "30 Seconds To Mars",
    "title": "From Yesterday",
    "timestamp": "2025-06-16T01:19:00+02:00"
  },
  {
    "time": "01:16",
    "artist": "Grandaddy",
    "title": "A.M. 180",
    "timestamp": "2025-06-16T01:16:00+02:00"
  },
  {
    "time": "01:11",
    "artist": "Wolf Alice",
    "title": "Bloom Baby Bloom",
    "timestamp": "2025-06-16T01:11:00+02:00"
  },
  {
    "time": "01:05",
    "artist": "Deep Purple",
    "title": "Smoke On The Water",
    "timestamp": "2025-06-16T01:05:00+02:00"
  },
  {
    "time": "01:02",
    "artist": "Kings Of Leon",
    "title": "Radioactive",
    "timestamp": "2025-06-16T01:02:00+02:00"
  },
  {
    "time": "00:52",
    "artist": "Cake",
    "title": "The Distance",
    "timestamp": "2025-06-16T00:52:00+02:00"
  },
  {
    "time": "00:48",
    "artist": "Rammstein",
    "title": "Deutschland",
    "timestamp": "2025-06-16T00:48:00+02:00"
  },
  {
    "time": "00:43",
    "artist": "Mumford and Sons",
    "title": "Roll Away Your Stone",
    "timestamp": "2025-06-16T00:43:00+02:00"
  },
  {
    "time": "00:40",
    "artist": "Wunderhorse",
    "title": "The Rope",
    "timestamp": "2025-06-16T00:40:00+02:00"
  },
  {
    "time": "00:34",
    "artist": "Pearl Jam",
    "title": "Black",
    "timestamp": "2025-06-16T00:34:00+02:00"
  },
  {
    "time": "00:26",
    "artist": "Incubus",
    "title": "Are You In",
    "timestamp": "2025-06-16T00:26:00+02:00"
  },
  {
    "time": "00:24",
    "artist": "Madness",
    "title": "One Step Beyond",
    "timestamp": "2025-06-16T00:24:00+02:00"
  },
  {
    "time": "00:19",
    "artist": "Bring Me The Horizon",
    "title": "Mother Tongue",
    "timestamp": "2025-06-16T00:19:00+02:00"
  },
  {
    "time": "00:16",
    "artist": "The Smashing Pumpkins",
    "title": "Disarm",
    "timestamp": "2025-06-16T00:16:00+02:00"
  },
  {
    "time": "00:13",
    "artist": "White Lies",
    "title": "Nothing On Me",
    "timestamp": "2025-06-16T00:13:00+02:00"
  },
  {
    "time": "00:05",
    "artist": "Temple Of The Dog",
    "title": "Say Hello 2 Heaven",
    "timestamp": "2025-06-16T00:05:00+02:00"
  },
  {
    "time": "00:03",
    "artist": "Florence The Machine",
    "title": "You Got The Love",
    "timestamp": "2025-06-16T00:03:00+02:00"
  }
]